mezze/__init__.py
mezze/asgi.py
mezze/settings.py
mezze/urls.py
mezze/wsgi.py
mezza-0.1.0.dist-info/LICENSE
mezza-0.1.0.dist-info/METADATA
mezza-0.1.0.dist-info/WHEEL
mezza-0.1.0.dist-info/RECORD
