Metadata-Version: 2.1
Name: mezza
Version: 0.1.0
Summary: Open-source Headless CMS powered by Django
License: BSD
Author: Karl Hobley
Author-email: karl@kaed.uk
Requires-Python: >=3.11,<4.0
Classifier: License :: Other/Proprietary License
Classifier: Programming Language :: Python :: 3
Classifier: Programming Language :: Python :: 3.11
Requires-Dist: Django (>=5.0.4,<6.0.0)
